shinestacker/__init__.py
shinestacker/_version.py
shinestacker/algorithms/__init__.py
shinestacker/algorithms/align.py
shinestacker/algorithms/align_auto.py
shinestacker/algorithms/align_parallel.py
shinestacker/algorithms/balance.py
shinestacker/algorithms/base_stack_algo.py
shinestacker/algorithms/corrections.py
shinestacker/algorithms/denoise.py
shinestacker/algorithms/depth_map.py
shinestacker/algorithms/exif.py
shinestacker/algorithms/feature_match.py
shinestacker/algorithms/multilayer.py
shinestacker/algorithms/noise_detection.py
shinestacker/algorithms/plot_manager.py
shinestacker/algorithms/pyramid.py
shinestacker/algorithms/pyramid_auto.py
shinestacker/algorithms/pyramid_tiles.py
shinestacker/algorithms/sharpen.py
shinestacker/algorithms/stack.py
shinestacker/algorithms/stack_framework.py
shinestacker/algorithms/tonemapping.py
shinestacker/algorithms/transform_estimate.py
shinestacker/algorithms/utils.py
shinestacker/algorithms/vignetting.py
shinestacker/algorithms/white_balance.py
shinestacker/app/__init__.py
shinestacker/app/about_dialog.py
shinestacker/app/args_parser_opts.py
shinestacker/app/gui_utils.py
shinestacker/app/help_menu.py
shinestacker/app/main.py
shinestacker/app/open_frames.py
shinestacker/app/project.py
shinestacker/app/retouch.py
shinestacker/app/settings_dialog.py
shinestacker/classic_project/__init__.py
shinestacker/classic_project/classic_element_action_manager.py
shinestacker/classic_project/classic_project_view.py
shinestacker/classic_project/classic_selection_state.py
shinestacker/classic_project/gui_run.py
shinestacker/classic_project/list_container.py
shinestacker/classic_project/tab_widget.py
shinestacker/common_project/__init__.py
shinestacker/common_project/element_action_manager.py
shinestacker/common_project/processing_widget.py
shinestacker/common_project/project_handler.py
shinestacker/common_project/project_undo_manager.py
shinestacker/common_project/project_view.py
shinestacker/common_project/run_worker.py
shinestacker-1.13.2.dist-info/licenses/LICENSE
shinestacker-1.13.2.dist-info/METADATA
shinestacker-1.13.2.dist-info/WHEEL
shinestacker-1.13.2.dist-info/entry_points.txt
shinestacker-1.13.2.dist-info/top_level.txt
shinestacker-1.13.2.dist-info/RECORD
