Metadata-Version: 2.4
Name: shinestacker
Version: 1.13.2
Summary: ShineStacker
Author-email: Luca Lista <luka.lista@gmail.com>
License-Expression: LGPL-3.0
Project-URL: Homepage, https://github.com/lucalista/shinestacker
Project-URL: Documentation, https://shinestacker.readthedocs.io/
Classifier: Programming Language :: Python :: 3
Classifier: Operating System :: OS Independent
Requires-Python: >=3.12
License-File: LICENSE
Requires-Dist: imagecodecs
Requires-Dist: ipywidgets
Requires-Dist: jsonpickle
Requires-Dist: matplotlib
Requires-Dist: numpy
Requires-Dist: opencv_python<4.12,>=4.11
Requires-Dist: pillow
Requires-Dist: psdtags
Requires-Dist: psutil
Requires-Dist: PySide6
Requires-Dist: scipy
Requires-Dist: tifffile
Requires-Dist: tqdm
Requires-Dist: setuptools-scm
Provides-Extra: dev
Requires-Dist: pytest; extra == "dev"
Dynamic: license-file
